sigstickers/__init__.py
sigstickers/__main__.py
sigstickers/caching.py
sigstickers/cli.py
sigstickers/downloader.py
sigstickers-2025.dist-info/METADATA
sigstickers-2025.dist-info/WHEEL
sigstickers-2025.dist-info/entry_points.txt
sigstickers-2025.dist-info/licenses/LICENSE.md
sigstickers-2025.dist-info/RECORD
