Metadata-Version: 2.4
Name: sigstickers
Version: 2025
Summary: Download sticker packs from Signal
Project-URL: Homepage, https://github.com/FHPythonUtils/SigStickers
Project-URL: Repository, https://github.com/FHPythonUtils/SigStickers
Project-URL: Documentation, https://github.com/FHPythonUtils/SigStickers/blob/master/README.md
Author: FredHappyface
License-Expression: MIT
License-File: LICENSE.md
Classifier: Development Status :: 5 - Production/Stable
Classifier: Intended Audience :: Developers
Classifier: Intended Audience :: Education
Classifier: Natural Language :: English
Classifier: Operating System :: OS Independent
Classifier: Programming Language :: Python :: Implementation :: CPython
Classifier: Topic :: Multimedia :: Graphics
Classifier: Topic :: Software Development :: Libraries :: Python Modules
Classifier: Topic :: Utilities
Requires-Python: >=3.9
Requires-Dist: emoji>=2.14.1
Requires-Dist: loguru>=0.7.3
Requires-Dist: pillow>=11.1.0
Requires-Dist: signalstickers-client>=3.3.0
